README.md
setup.cfg
setup.py
teigen/__init__.py
teigen/__main__.py
teigen/dictwidgetpg.py
teigen/dictwidgetqt.py
teigen/geometry3d.py
teigen/gui.py
teigen/iowidgetqt.py
teigen/measurement.py
teigen/postprocessing.py
teigen/simpleio.py
teigen/tablewidget.py
teigen/tb_lar.py
teigen/tb_lar_kunes.py
teigen/tb_lar_smooth.py
teigen/tb_volume.py
teigen/tb_vtk.py
teigen/teigendoc.py
teigen/tgmain.py
teigen/tree.py
teigen.egg-info/PKG-INFO
teigen.egg-info/SOURCES.txt
teigen.egg-info/dependency_links.txt
teigen.egg-info/requires.txt
teigen.egg-info/top_level.txt
teigen/generators/__init__.py
teigen/generators/cylinders.py
teigen/generators/cylindersqt.py
teigen/generators/general.py
teigen/generators/gensei_wrapper.py
teigen/generators/unconnected_cylinders.py
teigen/generators/unconnected_cylinders_qt.py