Metadata-Version: 1.1
Name: teigen
Version: 0.3.0
Summary: distribution to pypi and conda
Home-page: https://github.com/mjirik/teigen
Author: Miroslav Jirik
Author-email: miroslav.jirik@gmail.com
License: Apache v2
Keywords: dicom 3D read write
Platform: UNKNOWN
Classifier: Development Status :: 3 - Alpha
Classifier: Intended Audience :: Developers
Classifier: Topic :: Scientific/Engineering :: Bio-Informatics
Classifier: License :: OSI Approved :: BSD License
Classifier: Programming Language :: Python :: 2.7
